{
  "agreementId": {
    "type": "string"
  },
  "stateType": {
    "type": "string"
  },
  "id": {
    "type": "string"
  },
  "period": {
    "type": "object",
    "properties": {
      "from": {
        "type": "string"
      },
      "to": {
        "type": "string"
      }
    }
  },
  "scope": {
    "type": "object"
  },
  "window": {
    "type": "object",
    "properties": {
      "_type": {
        "type": "string"
      },
      "period": {
        "type": "string"
      }
    }
  },
  "records": {
    "type": "array",
    "items": {
      "type": "object",
      "properties": {
        "value": {
          "oneOf": [
            {
              "type": "string"
            },
            {
              "type": "number"
            },
            {
              "type": "boolean"
            }
          ]
        },
        "time": {
          "type": "string"
        }
      }
    }
  }
}
